{
  "number": 7,
  "name": "Agriculture",
  "latest_amended_on": "2025-09-26",
  "latest_issue_date": "2025-09-30",
  "up_to_date_as_of": "2025-09-30",
  "reserved": false,
  "checksum": "de40c026f715ea66d869c53b1d0b5ae8a404aca9312ab8f256cab5009594e516",
  "wordCount": 5633788,
  "agencySlug": "inspector-general-office-agriculture-department",
  "titleChapterCounts": {
    "title": "7",
    "chapter": "XXVI",
    "titleCount": 10,
    "chapterCount": 10,
    "titleDisplayHeading": "Title 7 | Agriculture",
    "chapterDisplayHeading": " Chapter XXVI | Office of Inspector General, Department of Agriculture",
    "raw": [
      {
        "path": "Title 7 > Subtitle B >  Chapter XXVI > Part 2610",
        "levels": [
          "title",
          "subtitle",
          "chapter",
          "subchapter",
          "part",
          "subpart",
          "subject_group"
        ],
        "headings": [
          "Agriculture",
          "Regulations of the Department of Agriculture",
          "Office of Inspector General, Department of Agriculture",
          "",
          "Organization, Functions, and Delegations of Authority",
          "",
          ""
        ],
        "type": "subject_group",
        "count": 5,
        "max_score": 2.0245311,
        "cfrReference": {
          "title": 7,
          "subtitle": "B",
          "chapter": "XXVI",
          "part": "2610"
        }
      },
      {
        "path": "Title 7 > Subtitle B >  Chapter XXVI > Part 2620",
        "levels": [
          "title",
          "subtitle",
          "chapter",
          "subchapter",
          "part",
          "subpart",
          "subject_group"
        ],
        "headings": [
          "Agriculture",
          "Regulations of the Department of Agriculture",
          "Office of Inspector General, Department of Agriculture",
          "",
          "Availability of Information to the Public",
          "",
          ""
        ],
        "type": "subject_group",
        "count": 5,
        "max_score": 2.0245311,
        "cfrReference": {
          "title": 7,
          "subtitle": "B",
          "chapter": "XXVI",
          "part": "2620"
        }
      }
    ]
  },
  "searchCount": 10,
  "versionSummary": {
    "titleNumber": 7,
    "totalVersions": 31108,
    "firstDate": "2016-05-04",
    "lastDate": "2025-09-26",
    "uniqueParts": 480,
    "uniqueSubparts": 313,
    "typeCounts": {
      "section": 30688,
      "appendix": 420
    }
  }
}